app/__init__.py
app/config.py
app/interface.py
app/main.py
app/process/__init__.py
app/process/encode_signal.py
app/process/get_original_signal.py
app/process/helpers.py
app/process/load_sound_wave.py
app/process/models.py
app/process/perform_fourier_analysis.py
app/process/makelab/__init__.py
app/process/makelab/audio.py
app/process/makelab/signal.py
sound_analyzer_encoder-0.1.dist-info/LICENSE
sound_analyzer_encoder-0.1.dist-info/METADATA
sound_analyzer_encoder-0.1.dist-info/WHEEL
sound_analyzer_encoder-0.1.dist-info/top_level.txt
sound_analyzer_encoder-0.1.dist-info/RECORD
